{
  "id": "Salamence",
  "spawnInfos": [
    {
      "spec": "species:Salamence",
      "stringLocationTypes": [
        "Air"
      ],
      "minLevel": 50,
      "maxLevel": 60,
      "typeID": "pokemon",
      "heldItems": [
        {
          "itemID": "pixelmon:dragon_fang",
          "percentChance": 5
        }
      ],
      "condition": {
        "times": [
          "NIGHT"
        ],
        "biomes": [
          "#pixelmon:spawning/mesas"
        ]
      },
      "rarity": 0.0
    },
    {
      "spec": "species:Salamence",
      "stringLocationTypes": [
        "Air"
      ],
      "minLevel": 50,
      "maxLevel": 60,
      "typeID": "pokemon",
      "heldItems": [
        {
          "itemID": "pixelmon:dragon_fang",
          "percentChance": 5
        }
      ],
      "condition": {
        "times": [
          "DAY"
        ],
        "biomes": [
          "pixelmon:ultra_crater"
        ]
      },
      "rarity": 0.0
    },
    {
      "spec": "species:Salamence palette:alter",
      "stringLocationTypes": [
        "Air"
      ],
      "minLevel": 50,
      "maxLevel": 60,
      "typeID": "pokemon",
      "heldItems": [
        {
          "itemID": "pixelmon:dragon_fang",
          "percentChance": 5
        }
      ],
      "condition": {
        "times": [
          "MIDDAY"
        ],
        "biomes": [
          "pixelmon:ultra_crater"
        ]
      },
      "rarity": 0.0
    }
  ]
}
