{
  "id": "Tinkatuff",
  "spawnInfos": [
    {
      "spec": "species:Tinkatuff",
      "stringLocationTypes": [
        "Land"
      ],
      "minLevel": 25,
      "maxLevel": 35,
      "typeID": "pokemon",
      "condition": {
        "times": [
          "DAY"
        ],
        "biomes": [
          "#pixelmon:spawning/mountainous_forests",
          "#pixelmon:spawning/redwoods"
        ]
      },
      "rarity": 30.0
    },
    {
      "spec": "species:Tinkatuff palette:witch",
      "stringLocationTypes": [
        "Land",
        "Manmade",
        "Indoors"
      ],
      "minLevel": 25,
      "maxLevel": 35,
      "typeID": "pokemon",
      "condition": {
        "times": [
          "NIGHT"
        ],
        "structures": [
          "pixelmon:pumpkin_house"
        ]
      },
      "rarity": 0.0
    },
    {
      "spec": "species:Tinkatuff palette:witch boss:haunted",
      "stringLocationTypes": [
        "Land",
        "Manmade",
        "Indoors"
      ],
      "minLevel": 25,
      "maxLevel": 35,
      "typeID": "pokemon",
      "condition": {
        "times": [
          "NIGHT"
        ],
        "structures": [
          "pixelmon:pumpkin_house"
        ]
      },
      "rarity": 0.0
    }
  ]
}
