{
  "id": "Whiscash",
  "spawnInfos": [
    {
      "spec": "species:Whiscash",
      "stringLocationTypes": [
        "Water"
      ],
      "minLevel": 35,
      "maxLevel": 50,
      "typeID": "pokemon",
      "condition": {
        "biomes": [
          "#pixelmon:spawning/swamps",
          "#pixelmon:spawning/lakes",
          "minecraft:river",
          "byg:polluted_lake"
        ]
      },
      "rarity": 0.0
    },
    {
      "spec": "species:Whiscash",
      "stringLocationTypes": [
        "Underground Water"
      ],
      "minLevel": 35,
      "maxLevel": 50,
      "typeID": "pokemon",
      "anticondition": {
        "biomes": [
          "#pixelmon:spawning/drowned"
        ]
      },
      "rarity": 0.0
    }
  ]
}
