{
  "interactions": {
    "values": [
      {
        "interactions": [
          {
            "event": "pixelmon:right_click",
            "conditions": {
              "type": "pixelmon:true"
            },
            "results": {
              "value": [
                {
                  "title": "     ",
                  "pages": [
                    "Hm, so they doubled the guests by using Pok\u00e9mon as attractions?",
                    "Hm, well, maybe I should make a cute Pok\u00e9mon our motel's mascot. I wonder if that will attract more guests to stay with us.",
                    "Oh, sorry, sorry! I was so absorbed in watching TV!",
                    "Since that Team came to town, the tourists have been staying away."
                  ],
                  "type": "pixelmon:open_paged_dialogue"
                }
              ],
              "type": "pixelmon:constant"
            }
          }
        ]
      }
    ],
    "type": "pixelmon:uniformly_random"
  },
  "models": {
    "values": [
      {
        "slim": false,
        "texture": {
          "resource": {
            "resource": "pixelmon:textures/steve/npcchat1.png",
            "fallback": "pixelmon:textures/steve/npcchat1.png"
          },
          "type": "pixelmon:fallback"
        },
        "type": "pixelmon:player"
      }
    ],
    "type": "pixelmon:uniformly_random"
  },
  "properties": {
    "value": {
      "health": 20.0,
      "eyeHeight": 1.5,
      "dimensions": {
        "width": 1.0,
        "height": 2.0
      },
      "pushable": false,
      "child": false,
      "invulnerable": true,
      "immovable": true,
      "nameplate": false
    },
    "type": "pixelmon:constant"
  },
  "party": {
    "value": {
      "type": "pixelmon:empty"
    },
    "type": "pixelmon:constant"
  },
  "names": {
    "values": [
      "     "
    ],
    "type": "pixelmon:uniformly_random"
  },
  "goals": {
    "type": "pixelmon:constant",
    "value": {
      "goals": [
        {
          "provider": {
            "type": "pixelmon:look_at_nearby",
            "look_distance": 5,
            "probability": 0.9
          },
          "priority": 1
        }
      ]
    }
  }
}