{
  "name": "Pawniard",
  "dex": 624,
  "defaultForms": [
    ""
  ],
  "forms": [
    {
      "name": "",
      "experienceGroup": "MEDIUM_FAST",
      "dimensions": {
        "height": 0.8,
        "width": 0.5,
        "length": 1,
        "eyeHeight": 0.8,
        "hoverHeight": 0.8
      },
      "moves": {
        "levelUpMoves": [
          {
            "level": 0,
            "attacks": [
              "Leer",
              "Scratch"
            ]
          },
          {
            "level": 5,
            "attacks": [
              "Fury Cutter"
            ]
          },
          {
            "level": 10,
            "attacks": [
              "Metal Claw"
            ]
          },
          {
            "level": 15,
            "attacks": [
              "Torment"
            ]
          },
          {
            "level": 20,
            "attacks": [
              "Scary Face"
            ]
          },
          {
            "level": 25,
            "attacks": [
              "Assurance"
            ]
          },
          {
            "level": 30,
            "attacks": [
              "Metal Sound"
            ]
          },
          {
            "level": 35,
            "attacks": [
              "Slash"
            ]
          },
          {
            "level": 40,
            "attacks": [
              "Night Slash"
            ]
          },
          {
            "level": 45,
            "attacks": [
              "Iron Defense"
            ]
          },
          {
            "level": 50,
            "attacks": [
              "Laser Focus"
            ]
          },
          {
            "level": 55,
            "attacks": [
              "Iron Head"
            ]
          },
          {
            "level": 60,
            "attacks": [
              "Swords Dance"
            ]
          },
          {
            "level": 65,
            "attacks": [
              "Guillotine"
            ]
          }
        ],
        "tutorMoves": [
          "Lash Out",
          "Steel Beam"
        ],
        "eggMoves": [
          "Headbutt",
          "Mean Look",
          "Quick Guard",
          "Sucker Punch"
        ],
        "tmMoves8": [
          "Thunder Wave",
          "Dig",
          "Screech",
          "Rest",
          "Thief",
          "Snore",
          "Protect",
          "Scary Face",
          "Attract",
          "Sandstorm",
          "Rain Dance",
          "Beat Up",
          "Facade",
          "Revenge",
          "Brick Break",
          "Rock Tomb",
          "Payback",
          "Assurance",
          "Fling",
          "Shadow Claw",
          "Psycho Cut",
          "Low Sweep",
          "Round",
          "Retaliate",
          "Snarl",
          "False Swipe"
        ],
        "trMoves": [
          "Swords Dance",
          "Low Kick",
          "Substitute",
          "Endure",
          "Sleep Talk",
          "Taunt",
          "Iron Defense",
          "Poison Jab",
          "Dark Pulse",
          "X-Scissor",
          "Iron Head",
          "Stealth Rock",
          "Grass Knot",
          "Foul Play"
        ],
        "hmMoves": [],
        "transferMoves": [
          "Aerial Ace",
          "Confide",
          "Cut",
          "Double Team",
          "Dual Chop",
          "Embargo",
          "Feint Attack",
          "Frustration",
          "Hidden Power",
          "Hone Claws",
          "Knock Off",
          "Magnet Rise",
          "Power-Up Punch",
          "Pursuit",
          "Return",
          "Rock Polish",
          "Rock Smash",
          "Role Play",
          "Secret Power",
          "Snatch",
          "Spite",
          "Swagger",
          "Toxic"
        ],
        "tmMoves7": [
          "Toxic",
          "Hidden Power",
          "Taunt",
          "Protect",
          "Rain Dance",
          "Frustration",
          "Return",
          "Brick Break",
          "Double Team",
          "Sandstorm",
          "Rock Tomb",
          "Aerial Ace",
          "Torment",
          "Facade",
          "Rest",
          "Attract",
          "Thief",
          "Low Sweep",
          "Round",
          "False Swipe",
          "Fling",
          "Embargo",
          "Shadow Claw",
          "Payback",
          "Rock Polish",
          "Thunder Wave",
          "Swords Dance",
          "X-Scissor",
          "Poison Jab",
          "Grass Knot",
          "Swagger",
          "Sleep Talk",
          "Substitute",
          "Snarl",
          "Dark Pulse",
          "Confide"
        ],
        "tmMoves6": [
          "Hone Claws",
          "Toxic",
          "Hidden Power",
          "Taunt",
          "Protect",
          "Rain Dance",
          "Frustration",
          "Return",
          "Dig",
          "Brick Break",
          "Double Team",
          "Sandstorm",
          "Rock Tomb",
          "Aerial Ace",
          "Torment",
          "Facade",
          "Rest",
          "Attract",
          "Thief",
          "Low Sweep",
          "Round",
          "False Swipe",
          "Fling",
          "Embargo",
          "Shadow Claw",
          "Payback",
          "Retaliate",
          "Rock Polish",
          "Thunder Wave",
          "Swords Dance",
          "X-Scissor",
          "Poison Jab",
          "Grass Knot",
          "Swagger",
          "Sleep Talk",
          "Substitute",
          "Secret Power",
          "Snarl",
          "Dark Pulse",
          "Power-Up Punch",
          "Confide"
        ],
        "tmMoves5": [
          "Hone Claws",
          "Toxic",
          "Hidden Power",
          "Taunt",
          "Protect",
          "Rain Dance",
          "Frustration",
          "Return",
          "Dig",
          "Brick Break",
          "Double Team",
          "Sandstorm",
          "Rock Tomb",
          "Aerial Ace",
          "Torment",
          "Facade",
          "Rest",
          "Attract",
          "Thief",
          "Low Sweep",
          "Round",
          "False Swipe",
          "Fling",
          "Embargo",
          "Shadow Claw",
          "Payback",
          "Retaliate",
          "Rock Polish",
          "Thunder Wave",
          "Swords Dance",
          "X-Scissor",
          "Poison Jab",
          "Grass Knot",
          "Swagger",
          "Substitute",
          "Rock Smash",
          "Snarl"
        ],
        "tmMoves4": [],
        "tmMoves3": [],
        "tmMoves2": [],
        "tmMoves1": [],
        "tmMoves": []
      },
      "abilities": {
        "abilities": [
          "Defiant",
          "InnerFocus"
        ],
        "hiddenAbilities": [
          "Pressure"
        ]
      },
      "movement": {
        "rideable": false,
        "canFly": false,
        "canSurf": false,
        "canRideShoulder": false
      },
      "aggression": {
        "timid": 0,
        "passive": 50,
        "aggressive": 50
      },
      "battleStats": {
        "hp": 45,
        "attack": 85,
        "defense": 70,
        "specialAttack": 40,
        "specialDefense": 40,
        "speed": 60
      },
      "tags": [],
      "spawn": {
        "baseExp": 68,
        "baseFriendship": 35,
        "spawnLevel": 15,
        "spawnLevelRange": 15,
        "spawnLocations": [
          "LAND"
        ]
      },
      "possibleGenders": [
        "MALE",
        "FEMALE"
      ],
      "genderProperties": [
        {
          "gender": "ALL",
          "palettes": [
            {
              "name": "none",
              "texture": "pixelmon:pokemon/624_pawniard/all/base/none/texture.png",
              "sprite": "pixelmon:pokemon/624_pawniard/all/base/none/sprite.png",
              "particle": "",
              "modelLocator": {
                "factoryType": "NORMAL",
                "pqc": [
                  "pixelmon:pokemon/624_pawniard/all/base/none/model.pqc"
                ]
              },
              "sounds": [
                "pixelmon.mob.pawniard"
              ]
            },
            {
              "name": "shiny",
              "texture": "pixelmon:pokemon/624_pawniard/all/base/shiny/texture.png",
              "sprite": "pixelmon:pokemon/624_pawniard/all/base/shiny/sprite.png",
              "particle": "arcanery:shiny"
            }
          ]
        }
      ],
      "eggGroups": [
        "HUMAN_LIKE"
      ],
      "types": [
        "DARK",
        "STEEL"
      ],
      "preEvolutions": [],
      "defaultBaseForm": "",
      "megaItems": [],
      "megas": [],
      "gigantamax": {
        "canHaveFactor": false,
        "canGigantamax": false
      },
      "eggCycles": 21,
      "weight": 10.2,
      "catchRate": 120,
      "malePercentage": 50,
      "evolutions": [
        {
          "level": 52,
          "to": "Bisharp",
          "conditions": [],
          "evoType": "leveling"
        }
      ],
      "evYields": {
        "attack": 1
      }
    }
  ],
  "generation": 5
}
